README.rst
setup.py
charlie_brown/__init__.py
charlie_brown/__main__.py
charlie_brown/_version.py
charlie_brown/main.hy
charlie_brown.egg-info/PKG-INFO
charlie_brown.egg-info/SOURCES.txt
charlie_brown.egg-info/dependency_links.txt
charlie_brown.egg-info/requires.txt
charlie_brown.egg-info/top_level.txt