Metadata-Version: 2.1
Name: charlie-brown
Version: 0.1.1
Summary: Check your email with IMAP IDLE and preview messages
Home-page: UNKNOWN
Author: Kodi B. Arfer
License: UNKNOWN
Project-URL: Source Code, https://github.com/Kodiologist/Charlie-Brown
Platform: UNKNOWN
Classifier: Programming Language :: Python :: 3
Classifier: License :: OSI Approved :: GNU General Public License v3 or later (GPLv3+)
Classifier: Operating System :: OS Independent
